fractaltext/__init__.py
fractaltext/annotate.py
fractaltext/item.py
fractaltext/parse.py
fractaltext/proofwrite.py
fractaltext/py.typed
fractaltext/serialize.py
fractaltext/naked/__init__.py
fractaltext-0.1.0.dist-info/METADATA
fractaltext-0.1.0.dist-info/WHEEL
fractaltext-0.1.0.dist-info/licenses/LICENSE
fractaltext-0.1.0.dist-info/RECORD
